{"chunk_definitions":[{"row":31,"row_count":1,"visible":true,"expansion_state":0,"options":{"engine":"r","label":"unnamed-chunk-227"},"document_id":"831D4666","chunk_id":"c37bgwzmszd1b","chunk_label":"unnamed-chunk-1"},{"row":38,"row_count":1,"visible":true,"expansion_state":0,"options":{"engine":"r","label":"unnamed-chunk-440"},"document_id":"831D4666","chunk_id":"c5t1vto2mqk7p","chunk_label":"unnamed-chunk-2"},{"row":78,"row_count":1,"visible":true,"expansion_state":0,"options":{"engine":"r","label":"unnamed-chunk-280"},"document_id":"831D4666","chunk_id":"csllaynr8hdbu","chunk_label":"unnamed-chunk-3"},{"row":125,"row_count":1,"visible":true,"expansion_state":0,"options":{"engine":"r","label":"unnamed-chunk-447"},"document_id":"831D4666","chunk_id":"cb4kja0o38ted","chunk_label":"unnamed-chunk-4"},{"row":133,"row_count":1,"visible":true,"expansion_state":0,"options":{"engine":"r","label":"unnamed-chunk-442"},"document_id":"831D4666","chunk_id":"c5xj7nw2cu7hq","chunk_label":"unnamed-chunk-5"},{"row":178,"row_count":1,"visible":true,"expansion_state":0,"options":{"engine":"r","label":"unnamed-chunk-443"},"document_id":"831D4666","chunk_id":"cm8o0k78rorma","chunk_label":"unnamed-chunk-6"}],"doc_write_time":1716567166,"chunk_rendered_width":700}